setup.py
xsj_distributions/Binomialdistribution.py
xsj_distributions/Gaussiandistribution.py
xsj_distributions/Generaldistribution.py
xsj_distributions/__init__.py
xsj_distributions.egg-info/PKG-INFO
xsj_distributions.egg-info/SOURCES.txt
xsj_distributions.egg-info/dependency_links.txt
xsj_distributions.egg-info/not-zip-safe
xsj_distributions.egg-info/top_level.txt